a2abase/__init__.py
a2abase/a2abase_client.py
a2abase/agent.py
a2abase/models.py
a2abase/tester_main.py
a2abase/thread.py
a2abase/tools.py
a2abase/api/__init__.py
a2abase/api/agents.py
a2abase/api/threads.py
a2abase/api/utils.py
a2abase-0.1.3.dist-info/METADATA
a2abase-0.1.3.dist-info/WHEEL
a2abase-0.1.3.dist-info/top_level.txt
a2abase-0.1.3.dist-info/RECORD
