Metadata-Version: 2.4
Name: a2abase
Version: 0.1.3
Summary: A2ABase SDK for Python
Author: BelArabyAI
License-Expression: MIT
Project-URL: Homepage, https://github.com/A2ABaseAI/sdks
Project-URL: Repository, https://github.com/A2ABaseAI/sdks
Project-URL: Issues, https://github.com/A2ABaseAI/sdks/issues
Keywords: a2abase,ai,sdk,agent,llm
Classifier: Development Status :: 4 - Beta
Classifier: Intended Audience :: Developers
Classifier: Programming Language :: Python :: 3
Classifier: Programming Language :: Python :: 3.11
Classifier: Programming Language :: Python :: 3.12
Requires-Python: >=3.11
Requires-Dist: httpx>=0.28.1
Requires-Dist: fastmcp>=2.10.6
